[
  {
    "Span": {
      "start": 0,
      "end": 26
    },
    "index": 1,
    "alignment_index": [
      "1"
    ]
  },
  {
    "Span": {
      "start": 27,
      "end": 170
    },
    "index": 2,
    "alignment_index": [
      "2"
    ]
  },
  {
    "Span": {
      "start": 171,
      "end": 353
    },
    "index": 3,
    "alignment_index": [
      "3"
    ]
  },
  {
    "Span": {
      "start": 354,
      "end": 354
    },
    "index": 4,
    "alignment_index": [
      "4"
    ]
  },
  {
    "Span": {
      "start": 355,
      "end": 574
    },
    "index": 5,
    "alignment_index": [
      "5"
    ]
  },
  {
    "Span": {
      "start": 575,
      "end": 811
    },
    "index": 6,
    "alignment_index": [
      "6"
    ]
  },
  {
    "Span": {
      "start": 812,
      "end": 1016
    },
    "index": 7,
    "alignment_index": [
      "7"
    ]
  },
  {
    "Span": {
      "start": 1017,
      "end": 1297
    },
    "index": 8,
    "alignment_index": [
      "8"
    ]
  },
  {
    "Span": {
      "start": 1298,
      "end": 1551
    },
    "index": 9,
    "alignment_index": [
      "9"
    ]
  },
  {
    "Span": {
      "start": 1552,
      "end": 1757
    },
    "index": 10,
    "alignment_index": [
      "10"
    ]
  },
  {
    "Span": {
      "start": 1758,
      "end": 1974
    },
    "index": 11,
    "alignment_index": [
      "11"
    ]
  },
  {
    "Span": {
      "start": 1975,
      "end": 2216
    },
    "index": 12,
    "alignment_index": [
      "12"
    ]
  },
  {
    "Span": {
      "start": 2217,
      "end": 2479
    },
    "index": 13,
    "alignment_index": [
      "13"
    ]
  },
  {
    "Span": {
      "start": 2480,
      "end": 2751
    },
    "index": 14,
    "alignment_index": [
      "14"
    ]
  },
  {
    "Span": {
      "start": 2752,
      "end": 3005
    },
    "index": 15,
    "alignment_index": [
      "15"
    ]
  },
  {
    "Span": {
      "start": 3006,
      "end": 3254
    },
    "index": 16,
    "alignment_index": [
      "16"
    ]
  },
  {
    "Span": {
      "start": 3255,
      "end": 3514
    },
    "index": 17,
    "alignment_index": [
      "17"
    ]
  },
  {
    "Span": {
      "start": 3515,
      "end": 3692
    },
    "index": 18,
    "alignment_index": [
      "18"
    ]
  },
  {
    "Span": {
      "start": 3693,
      "end": 3986
    },
    "index": 19,
    "alignment_index": [
      "19"
    ]
  },
  {
    "Span": {
      "start": 3987,
      "end": 4257
    },
    "index": 20,
    "alignment_index": [
      "20"
    ]
  },
  {
    "Span": {
      "start": 4258,
      "end": 4476
    },
    "index": 21,
    "alignment_index": [
      "21"
    ]
  },
  {
    "Span": {
      "start": 4477,
      "end": 4706
    },
    "index": 22,
    "alignment_index": [
      "22"
    ]
  },
  {
    "Span": {
      "start": 4707,
      "end": 4892
    },
    "index": 23,
    "alignment_index": [
      "23"
    ]
  },
  {
    "Span": {
      "start": 4893,
      "end": 5079
    },
    "index": 24,
    "alignment_index": [
      "24"
    ]
  },
  {
    "Span": {
      "start": 5080,
      "end": 5350
    },
    "index": 25,
    "alignment_index": [
      "25"
    ]
  },
  {
    "Span": {
      "start": 5351,
      "end": 5606
    },
    "index": 26,
    "alignment_index": [
      "26"
    ]
  },
  {
    "Span": {
      "start": 5607,
      "end": 5814
    },
    "index": 27,
    "alignment_index": [
      "27"
    ]
  },
  {
    "Span": {
      "start": 5815,
      "end": 6050
    },
    "index": 28,
    "alignment_index": [
      "28"
    ]
  },
  {
    "Span": {
      "start": 6051,
      "end": 6311
    },
    "index": 29,
    "alignment_index": [
      "29"
    ]
  },
  {
    "Span": {
      "start": 6312,
      "end": 6534
    },
    "index": 30,
    "alignment_index": [
      "30"
    ]
  },
  {
    "Span": {
      "start": 6535,
      "end": 6724
    },
    "index": 31,
    "alignment_index": [
      "31"
    ]
  },
  {
    "Span": {
      "start": 6725,
      "end": 6974
    },
    "index": 32,
    "alignment_index": [
      "32"
    ]
  },
  {
    "Span": {
      "start": 6975,
      "end": 6975
    },
    "index": 33,
    "alignment_index": [
      "33"
    ]
  },
  {
    "Span": {
      "start": 6976,
      "end": 7015
    },
    "index": 34,
    "alignment_index": [
      "34"
    ]
  },
  {
    "Span": {
      "start": 7016,
      "end": 7226
    },
    "index": 35,
    "alignment_index": [
      "35"
    ]
  },
  {
    "Span": {
      "start": 7227,
      "end": 7433
    },
    "index": 36,
    "alignment_index": [
      "36"
    ]
  },
  {
    "Span": {
      "start": 7434,
      "end": 7685
    },
    "index": 37,
    "alignment_index": [
      "37"
    ]
  },
  {
    "Span": {
      "start": 7686,
      "end": 7910
    },
    "index": 38,
    "alignment_index": [
      "38"
    ]
  },
  {
    "Span": {
      "start": 7911,
      "end": 8126
    },
    "index": 39,
    "alignment_index": [
      "39"
    ]
  },
  {
    "Span": {
      "start": 8127,
      "end": 8368
    },
    "index": 40,
    "alignment_index": [
      "40"
    ]
  },
  {
    "Span": {
      "start": 8369,
      "end": 8713
    },
    "index": 41,
    "alignment_index": [
      "41"
    ]
  },
  {
    "Span": {
      "start": 8714,
      "end": 9028
    },
    "index": 42,
    "alignment_index": [
      "42"
    ]
  },
  {
    "Span": {
      "start": 9029,
      "end": 9211
    },
    "index": 43,
    "alignment_index": [
      "43"
    ]
  },
  {
    "Span": {
      "start": 9212,
      "end": 9359
    },
    "index": 44,
    "alignment_index": [
      "44"
    ]
  },
  {
    "Span": {
      "start": 9360,
      "end": 9616
    },
    "index": 45,
    "alignment_index": [
      "45"
    ]
  },
  {
    "Span": {
      "start": 9617,
      "end": 9818
    },
    "index": 46,
    "alignment_index": [
      "46"
    ]
  },
  {
    "Span": {
      "start": 9819,
      "end": 9984
    },
    "index": 47,
    "alignment_index": [
      "47"
    ]
  },
  {
    "Span": {
      "start": 9985,
      "end": 9985
    },
    "index": 48,
    "alignment_index": [
      "48"
    ]
  },
  {
    "Span": {
      "start": 9986,
      "end": 9986
    },
    "index": 49,
    "alignment_index": [
      "49"
    ]
  },
  {
    "Span": {
      "start": 9987,
      "end": 10204
    },
    "index": 50,
    "alignment_index": [
      "50"
    ]
  },
  {
    "Span": {
      "start": 10205,
      "end": 10398
    },
    "index": 51,
    "alignment_index": [
      "51"
    ]
  },
  {
    "Span": {
      "start": 10399,
      "end": 10565
    },
    "index": 52,
    "alignment_index": [
      "52"
    ]
  },
  {
    "Span": {
      "start": 10566,
      "end": 10784
    },
    "index": 53,
    "alignment_index": [
      "53"
    ]
  },
  {
    "Span": {
      "start": 10785,
      "end": 11005
    },
    "index": 54,
    "alignment_index": [
      "54"
    ]
  },
  {
    "Span": {
      "start": 11006,
      "end": 11274
    },
    "index": 55,
    "alignment_index": [
      "55"
    ]
  },
  {
    "Span": {
      "start": 11275,
      "end": 11494
    },
    "index": 56,
    "alignment_index": [
      "56"
    ]
  },
  {
    "Span": {
      "start": 11495,
      "end": 11694
    },
    "index": 57,
    "alignment_index": [
      "57"
    ]
  },
  {
    "Span": {
      "start": 11695,
      "end": 11695
    },
    "index": 58,
    "alignment_index": [
      "58"
    ]
  },
  {
    "Span": {
      "start": 11696,
      "end": 11696
    },
    "index": 59,
    "alignment_index": [
      "59"
    ]
  },
  {
    "Span": {
      "start": 11697,
      "end": 11928
    },
    "index": 60,
    "alignment_index": [
      "60"
    ]
  },
  {
    "Span": {
      "start": 11929,
      "end": 12207
    },
    "index": 61,
    "alignment_index": [
      "61"
    ]
  },
  {
    "Span": {
      "start": 12208,
      "end": 12471
    },
    "index": 62,
    "alignment_index": [
      "62"
    ]
  },
  {
    "Span": {
      "start": 12472,
      "end": 12703
    },
    "index": 63,
    "alignment_index": [
      "63"
    ]
  },
  {
    "Span": {
      "start": 12704,
      "end": 12932
    },
    "index": 64,
    "alignment_index": [
      "64"
    ]
  },
  {
    "Span": {
      "start": 12933,
      "end": 13137
    },
    "index": 65,
    "alignment_index": [
      "65"
    ]
  },
  {
    "Span": {
      "start": 13138,
      "end": 13312
    },
    "index": 66,
    "alignment_index": [
      "66"
    ]
  },
  {
    "Span": {
      "start": 13313,
      "end": 13313
    },
    "index": 67,
    "alignment_index": [
      "67"
    ]
  },
  {
    "Span": {
      "start": 13314,
      "end": 13314
    },
    "index": 68,
    "alignment_index": [
      "68"
    ]
  },
  {
    "Span": {
      "start": 13315,
      "end": 13482
    },
    "index": 69,
    "alignment_index": [
      "69"
    ]
  },
  {
    "Span": {
      "start": 13483,
      "end": 13679
    },
    "index": 70,
    "alignment_index": [
      "70"
    ]
  },
  {
    "Span": {
      "start": 13680,
      "end": 13920
    },
    "index": 71,
    "alignment_index": [
      "71"
    ]
  },
  {
    "Span": {
      "start": 13921,
      "end": 14160
    },
    "index": 72,
    "alignment_index": [
      "72"
    ]
  },
  {
    "Span": {
      "start": 14161,
      "end": 14363
    },
    "index": 73,
    "alignment_index": [
      "73"
    ]
  },
  {
    "Span": {
      "start": 14364,
      "end": 14609
    },
    "index": 74,
    "alignment_index": [
      "74"
    ]
  },
  {
    "Span": {
      "start": 14610,
      "end": 14792
    },
    "index": 75,
    "alignment_index": [
      "75"
    ]
  },
  {
    "Span": {
      "start": 14793,
      "end": 14987
    },
    "index": 76,
    "alignment_index": [
      "76"
    ]
  },
  {
    "Span": {
      "start": 14988,
      "end": 15307
    },
    "index": 77,
    "alignment_index": [
      "77"
    ]
  },
  {
    "Span": {
      "start": 15308,
      "end": 15308
    },
    "index": 78,
    "alignment_index": [
      "78"
    ]
  },
  {
    "Span": {
      "start": 15309,
      "end": 15309
    },
    "index": 79,
    "alignment_index": [
      "79"
    ]
  },
  {
    "Span": {
      "start": 15310,
      "end": 15596
    },
    "index": 80,
    "alignment_index": [
      "80"
    ]
  },
  {
    "Span": {
      "start": 15597,
      "end": 15797
    },
    "index": 81,
    "alignment_index": [
      "81"
    ]
  },
  {
    "Span": {
      "start": 15798,
      "end": 15988
    },
    "index": 82,
    "alignment_index": [
      "82"
    ]
  },
  {
    "Span": {
      "start": 15989,
      "end": 16216
    },
    "index": 83,
    "alignment_index": [
      "83"
    ]
  },
  {
    "Span": {
      "start": 16217,
      "end": 16501
    },
    "index": 84,
    "alignment_index": [
      "84"
    ]
  },
  {
    "Span": {
      "start": 16502,
      "end": 16760
    },
    "index": 85,
    "alignment_index": [
      "85"
    ]
  },
  {
    "Span": {
      "start": 16761,
      "end": 17094
    },
    "index": 86,
    "alignment_index": [
      "86"
    ]
  },
  {
    "Span": {
      "start": 17095,
      "end": 17410
    },
    "index": 87,
    "alignment_index": [
      "87"
    ]
  },
  {
    "Span": {
      "start": 17411,
      "end": 17637
    },
    "index": 88,
    "alignment_index": [
      "88"
    ]
  },
  {
    "Span": {
      "start": 17638,
      "end": 17638
    },
    "index": 89,
    "alignment_index": [
      "89"
    ]
  },
  {
    "Span": {
      "start": 17639,
      "end": 17639
    },
    "index": 90,
    "alignment_index": [
      "90"
    ]
  },
  {
    "Span": {
      "start": 17640,
      "end": 17969
    },
    "index": 91,
    "alignment_index": [
      "91"
    ]
  },
  {
    "Span": {
      "start": 17970,
      "end": 18248
    },
    "index": 92,
    "alignment_index": [
      "92"
    ]
  },
  {
    "Span": {
      "start": 18249,
      "end": 18491
    },
    "index": 93,
    "alignment_index": [
      "93"
    ]
  },
  {
    "Span": {
      "start": 18492,
      "end": 18752
    },
    "index": 94,
    "alignment_index": [
      "94"
    ]
  },
  {
    "Span": {
      "start": 18753,
      "end": 19007
    },
    "index": 95,
    "alignment_index": [
      "95"
    ]
  },
  {
    "Span": {
      "start": 19008,
      "end": 19231
    },
    "index": 96,
    "alignment_index": [
      "96"
    ]
  },
  {
    "Span": {
      "start": 19232,
      "end": 19416
    },
    "index": 97,
    "alignment_index": [
      "97"
    ]
  },
  {
    "Span": {
      "start": 19417,
      "end": 19417
    },
    "index": 98,
    "alignment_index": [
      "98"
    ]
  },
  {
    "Span": {
      "start": 19418,
      "end": 19418
    },
    "index": 99,
    "alignment_index": [
      "99"
    ]
  },
  {
    "Span": {
      "start": 19419,
      "end": 19648
    },
    "index": 100,
    "alignment_index": [
      "100"
    ]
  },
  {
    "Span": {
      "start": 19649,
      "end": 19961
    },
    "index": 101,
    "alignment_index": [
      "101"
    ]
  },
  {
    "Span": {
      "start": 19962,
      "end": 20217
    },
    "index": 102,
    "alignment_index": [
      "102"
    ]
  },
  {
    "Span": {
      "start": 20218,
      "end": 20461
    },
    "index": 103,
    "alignment_index": [
      "103"
    ]
  },
  {
    "Span": {
      "start": 20462,
      "end": 20462
    },
    "index": 104,
    "alignment_index": [
      "104"
    ]
  },
  {
    "Span": {
      "start": 20463,
      "end": 20463
    },
    "index": 105,
    "alignment_index": [
      "105"
    ]
  },
  {
    "Span": {
      "start": 20464,
      "end": 20685
    },
    "index": 106,
    "alignment_index": [
      "106"
    ]
  },
  {
    "Span": {
      "start": 20686,
      "end": 20946
    },
    "index": 107,
    "alignment_index": [
      "107"
    ]
  },
  {
    "Span": {
      "start": 20947,
      "end": 20947
    },
    "index": 108,
    "alignment_index": [
      "108"
    ]
  },
  {
    "Span": {
      "start": 20948,
      "end": 20948
    },
    "index": 109,
    "alignment_index": [
      "109"
    ]
  },
  {
    "Span": {
      "start": 20949,
      "end": 21242
    },
    "index": 110,
    "alignment_index": [
      "110"
    ]
  },
  {
    "Span": {
      "start": 21243,
      "end": 21456
    },
    "index": 111,
    "alignment_index": [
      "111"
    ]
  },
  {
    "Span": {
      "start": 21457,
      "end": 21668
    },
    "index": 112,
    "alignment_index": [
      "112"
    ]
  },
  {
    "Span": {
      "start": 21669,
      "end": 21886
    },
    "index": 113,
    "alignment_index": [
      "113"
    ]
  },
  {
    "Span": {
      "start": 21887,
      "end": 22120
    },
    "index": 114,
    "alignment_index": [
      "114"
    ]
  },
  {
    "Span": {
      "start": 22121,
      "end": 22357
    },
    "index": 115,
    "alignment_index": [
      "115"
    ]
  },
  {
    "Span": {
      "start": 22358,
      "end": 22605
    },
    "index": 116,
    "alignment_index": [
      "116"
    ]
  },
  {
    "Span": {
      "start": 22606,
      "end": 22816
    },
    "index": 117,
    "alignment_index": [
      "117"
    ]
  },
  {
    "Span": {
      "start": 22817,
      "end": 23072
    },
    "index": 118,
    "alignment_index": [
      "118"
    ]
  },
  {
    "Span": {
      "start": 23073,
      "end": 23347
    },
    "index": 119,
    "alignment_index": [
      "119"
    ]
  },
  {
    "Span": {
      "start": 23348,
      "end": 23348
    },
    "index": 120,
    "alignment_index": [
      "120"
    ]
  },
  {
    "Span": {
      "start": 23349,
      "end": 23349
    },
    "index": 121,
    "alignment_index": [
      "121"
    ]
  },
  {
    "Span": {
      "start": 23350,
      "end": 23549
    },
    "index": 122,
    "alignment_index": [
      "122"
    ]
  },
  {
    "Span": {
      "start": 23550,
      "end": 23767
    },
    "index": 123,
    "alignment_index": [
      "123"
    ]
  },
  {
    "Span": {
      "start": 23768,
      "end": 24031
    },
    "index": 124,
    "alignment_index": [
      "124"
    ]
  },
  {
    "Span": {
      "start": 24032,
      "end": 24256
    },
    "index": 125,
    "alignment_index": [
      "125"
    ]
  },
  {
    "Span": {
      "start": 24257,
      "end": 24437
    },
    "index": 126,
    "alignment_index": [
      "126"
    ]
  },
  {
    "Span": {
      "start": 24438,
      "end": 24650
    },
    "index": 127,
    "alignment_index": [
      "127"
    ]
  },
  {
    "Span": {
      "start": 24651,
      "end": 24851
    },
    "index": 128,
    "alignment_index": [
      "128"
    ]
  },
  {
    "Span": {
      "start": 24852,
      "end": 25035
    },
    "index": 129,
    "alignment_index": [
      "129"
    ]
  },
  {
    "Span": {
      "start": 25036,
      "end": 25544
    },
    "index": 130,
    "alignment_index": [
      "130"
    ]
  },
  {
    "Span": {
      "start": 25545,
      "end": 25778
    },
    "index": 131,
    "alignment_index": [
      "131"
    ]
  },
  {
    "Span": {
      "start": 25779,
      "end": 25779
    },
    "index": 132,
    "alignment_index": [
      "132"
    ]
  },
  {
    "Span": {
      "start": 25780,
      "end": 25780
    },
    "index": 133,
    "alignment_index": [
      "133"
    ]
  },
  {
    "Span": {
      "start": 25781,
      "end": 25973
    },
    "index": 134,
    "alignment_index": [
      "134"
    ]
  },
  {
    "Span": {
      "start": 25974,
      "end": 26194
    },
    "index": 135,
    "alignment_index": [
      "135"
    ]
  },
  {
    "Span": {
      "start": 26195,
      "end": 26432
    },
    "index": 136,
    "alignment_index": [
      "136"
    ]
  },
  {
    "Span": {
      "start": 26433,
      "end": 26691
    },
    "index": 137,
    "alignment_index": [
      "137"
    ]
  },
  {
    "Span": {
      "start": 26692,
      "end": 26934
    },
    "index": 138,
    "alignment_index": [
      "138"
    ]
  },
  {
    "Span": {
      "start": 26935,
      "end": 27189
    },
    "index": 139,
    "alignment_index": [
      "139"
    ]
  },
  {
    "Span": {
      "start": 27190,
      "end": 27432
    },
    "index": 140,
    "alignment_index": [
      "140"
    ]
  },
  {
    "Span": {
      "start": 27433,
      "end": 27639
    },
    "index": 141,
    "alignment_index": [
      "141"
    ]
  },
  {
    "Span": {
      "start": 27640,
      "end": 27870
    },
    "index": 142,
    "alignment_index": [
      "142"
    ]
  },
  {
    "Span": {
      "start": 27871,
      "end": 27871
    },
    "index": 143,
    "alignment_index": [
      "143"
    ]
  },
  {
    "Span": {
      "start": 27872,
      "end": 27872
    },
    "index": 144,
    "alignment_index": [
      "144"
    ]
  },
  {
    "Span": {
      "start": 27873,
      "end": 28081
    },
    "index": 145,
    "alignment_index": [
      "145"
    ]
  },
  {
    "Span": {
      "start": 28082,
      "end": 28292
    },
    "index": 146,
    "alignment_index": [
      "146"
    ]
  },
  {
    "Span": {
      "start": 28293,
      "end": 28293
    },
    "index": 147,
    "alignment_index": [
      "147"
    ]
  },
  {
    "Span": {
      "start": 28294,
      "end": 28294
    },
    "index": 148,
    "alignment_index": [
      "148"
    ]
  },
  {
    "Span": {
      "start": 28295,
      "end": 28601
    },
    "index": 149,
    "alignment_index": [
      "149"
    ]
  },
  {
    "Span": {
      "start": 28602,
      "end": 28833
    },
    "index": 150,
    "alignment_index": [
      "150"
    ]
  },
  {
    "Span": {
      "start": 28834,
      "end": 28969
    },
    "index": 151,
    "alignment_index": [
      "151"
    ]
  },
  {
    "Span": {
      "start": 28970,
      "end": 29123
    },
    "index": 152,
    "alignment_index": [
      "152"
    ]
  },
  {
    "Span": {
      "start": 29124,
      "end": 29388
    },
    "index": 153,
    "alignment_index": [
      "153"
    ]
  },
  {
    "Span": {
      "start": 29389,
      "end": 29625
    },
    "index": 154,
    "alignment_index": [
      "154"
    ]
  },
  {
    "Span": {
      "start": 29626,
      "end": 29838
    },
    "index": 155,
    "alignment_index": [
      "155"
    ]
  },
  {
    "Span": {
      "start": 29839,
      "end": 30096
    },
    "index": 156,
    "alignment_index": [
      "156"
    ]
  },
  {
    "Span": {
      "start": 30097,
      "end": 30311
    },
    "index": 157,
    "alignment_index": [
      "157"
    ]
  },
  {
    "Span": {
      "start": 30312,
      "end": 30585
    },
    "index": 158,
    "alignment_index": [
      "158"
    ]
  },
  {
    "Span": {
      "start": 30586,
      "end": 30586
    },
    "index": 159,
    "alignment_index": [
      "159"
    ]
  },
  {
    "Span": {
      "start": 30587,
      "end": 30587
    },
    "index": 160,
    "alignment_index": [
      "160"
    ]
  },
  {
    "Span": {
      "start": 30588,
      "end": 30797
    },
    "index": 161,
    "alignment_index": [
      "161"
    ]
  },
  {
    "Span": {
      "start": 30798,
      "end": 31052
    },
    "index": 162,
    "alignment_index": [
      "162"
    ]
  },
  {
    "Span": {
      "start": 31053,
      "end": 31262
    },
    "index": 163,
    "alignment_index": [
      "163"
    ]
  },
  {
    "Span": {
      "start": 31263,
      "end": 31503
    },
    "index": 164,
    "alignment_index": [
      "164"
    ]
  },
  {
    "Span": {
      "start": 31504,
      "end": 31733
    },
    "index": 165,
    "alignment_index": [
      "165"
    ]
  },
  {
    "Span": {
      "start": 31734,
      "end": 31964
    },
    "index": 166,
    "alignment_index": [
      "166"
    ]
  },
  {
    "Span": {
      "start": 31965,
      "end": 32206
    },
    "index": 167,
    "alignment_index": [
      "167"
    ]
  },
  {
    "Span": {
      "start": 32207,
      "end": 32499
    },
    "index": 168,
    "alignment_index": [
      "168"
    ]
  },
  {
    "Span": {
      "start": 32500,
      "end": 32500
    },
    "index": 169,
    "alignment_index": [
      "169"
    ]
  },
  {
    "Span": {
      "start": 32501,
      "end": 32501
    },
    "index": 170,
    "alignment_index": [
      "170"
    ]
  },
  {
    "Span": {
      "start": 32502,
      "end": 32687
    },
    "index": 171,
    "alignment_index": [
      "171"
    ]
  },
  {
    "Span": {
      "start": 32688,
      "end": 32870
    },
    "index": 172,
    "alignment_index": [
      "172"
    ]
  },
  {
    "Span": {
      "start": 32871,
      "end": 33089
    },
    "index": 173,
    "alignment_index": [
      "173"
    ]
  },
  {
    "Span": {
      "start": 33090,
      "end": 33324
    },
    "index": 174,
    "alignment_index": [
      "174"
    ]
  },
  {
    "Span": {
      "start": 33325,
      "end": 33577
    },
    "index": 175,
    "alignment_index": [
      "175"
    ]
  },
  {
    "Span": {
      "start": 33578,
      "end": 33824
    },
    "index": 176,
    "alignment_index": [
      "176"
    ]
  },
  {
    "Span": {
      "start": 33825,
      "end": 33825
    },
    "index": 177,
    "alignment_index": [
      "177"
    ]
  },
  {
    "Span": {
      "start": 33826,
      "end": 33826
    },
    "index": 178,
    "alignment_index": [
      "178"
    ]
  },
  {
    "Span": {
      "start": 33827,
      "end": 34105
    },
    "index": 179,
    "alignment_index": [
      "179"
    ]
  },
  {
    "Span": {
      "start": 34106,
      "end": 34315
    },
    "index": 180,
    "alignment_index": [
      "180"
    ]
  },
  {
    "Span": {
      "start": 34316,
      "end": 34604
    },
    "index": 181,
    "alignment_index": [
      "181"
    ]
  },
  {
    "Span": {
      "start": 34605,
      "end": 34892
    },
    "index": 182,
    "alignment_index": [
      "182"
    ]
  },
  {
    "Span": {
      "start": 34893,
      "end": 35194
    },
    "index": 183,
    "alignment_index": [
      "183"
    ]
  },
  {
    "Span": {
      "start": 35195,
      "end": 35482
    },
    "index": 184,
    "alignment_index": [
      "184"
    ]
  },
  {
    "Span": {
      "start": 35483,
      "end": 35734
    },
    "index": 185,
    "alignment_index": [
      "185"
    ]
  },
  {
    "Span": {
      "start": 35735,
      "end": 35735
    },
    "index": 186,
    "alignment_index": [
      "186"
    ]
  },
  {
    "Span": {
      "start": 35736,
      "end": 35736
    },
    "index": 187,
    "alignment_index": [
      "187"
    ]
  },
  {
    "Span": {
      "start": 35737,
      "end": 35991
    },
    "index": 188,
    "alignment_index": [
      "188"
    ]
  },
  {
    "Span": {
      "start": 35992,
      "end": 36200
    },
    "index": 189,
    "alignment_index": [
      "189"
    ]
  },
  {
    "Span": {
      "start": 36201,
      "end": 36411
    },
    "index": 190,
    "alignment_index": [
      "190"
    ]
  },
  {
    "Span": {
      "start": 36412,
      "end": 36647
    },
    "index": 191,
    "alignment_index": [
      "191"
    ]
  },
  {
    "Span": {
      "start": 36648,
      "end": 36909
    },
    "index": 192,
    "alignment_index": [
      "192"
    ]
  },
  {
    "Span": {
      "start": 36910,
      "end": 37098
    },
    "index": 193,
    "alignment_index": [
      "193"
    ]
  },
  {
    "Span": {
      "start": 37099,
      "end": 37306
    },
    "index": 194,
    "alignment_index": [
      "194"
    ]
  },
  {
    "Span": {
      "start": 37307,
      "end": 37683
    },
    "index": 195,
    "alignment_index": [
      "195"
    ]
  },
  {
    "Span": {
      "start": 37684,
      "end": 37684
    },
    "index": 196,
    "alignment_index": [
      "196"
    ]
  },
  {
    "Span": {
      "start": 37685,
      "end": 37685
    },
    "index": 197,
    "alignment_index": [
      "197"
    ]
  },
  {
    "Span": {
      "start": 37686,
      "end": 37886
    },
    "index": 198,
    "alignment_index": [
      "198"
    ]
  },
  {
    "Span": {
      "start": 37887,
      "end": 38091
    },
    "index": 199,
    "alignment_index": [
      "199"
    ]
  },
  {
    "Span": {
      "start": 38092,
      "end": 38312
    },
    "index": 200,
    "alignment_index": [
      "200"
    ]
  },
  {
    "Span": {
      "start": 38313,
      "end": 38313
    },
    "index": 201,
    "alignment_index": [
      "201"
    ]
  },
  {
    "Span": {
      "start": 38314,
      "end": 38550
    },
    "index": 202,
    "alignment_index": [
      "202"
    ]
  },
  {
    "Span": {
      "start": 38551,
      "end": 38780
    },
    "index": 203,
    "alignment_index": [
      "203"
    ]
  },
  {
    "Span": {
      "start": 38781,
      "end": 39009
    },
    "index": 204,
    "alignment_index": [
      "204"
    ]
  },
  {
    "Span": {
      "start": 39010,
      "end": 39221
    },
    "index": 205,
    "alignment_index": [
      "205"
    ]
  },
  {
    "Span": {
      "start": 39222,
      "end": 39222
    },
    "index": 206,
    "alignment_index": [
      "206"
    ]
  },
  {
    "Span": {
      "start": 39223,
      "end": 39223
    },
    "index": 207,
    "alignment_index": [
      "207"
    ]
  },
  {
    "Span": {
      "start": 39224,
      "end": 39468
    },
    "index": 208,
    "alignment_index": [
      "208"
    ]
  },
  {
    "Span": {
      "start": 39469,
      "end": 39710
    },
    "index": 209,
    "alignment_index": [
      "209"
    ]
  },
  {
    "Span": {
      "start": 39711,
      "end": 39918
    },
    "index": 210,
    "alignment_index": [
      "210"
    ]
  },
  {
    "Span": {
      "start": 39919,
      "end": 40135
    },
    "index": 211,
    "alignment_index": [
      "211"
    ]
  },
  {
    "Span": {
      "start": 40136,
      "end": 40339
    },
    "index": 212,
    "alignment_index": [
      "212"
    ]
  },
  {
    "Span": {
      "start": 40340,
      "end": 40567
    },
    "index": 213,
    "alignment_index": [
      "213"
    ]
  },
  {
    "Span": {
      "start": 40568,
      "end": 40792
    },
    "index": 214,
    "alignment_index": [
      "214"
    ]
  },
  {
    "Span": {
      "start": 40793,
      "end": 41021
    },
    "index": 215,
    "alignment_index": [
      "215"
    ]
  },
  {
    "Span": {
      "start": 41022,
      "end": 41380
    },
    "index": 216,
    "alignment_index": [
      "216"
    ]
  },
  {
    "Span": {
      "start": 41381,
      "end": 41610
    },
    "index": 217,
    "alignment_index": [
      "217"
    ]
  },
  {
    "Span": {
      "start": 41611,
      "end": 41836
    },
    "index": 218,
    "alignment_index": [
      "218"
    ]
  },
  {
    "Span": {
      "start": 41837,
      "end": 42084
    },
    "index": 219,
    "alignment_index": [
      "219"
    ]
  },
  {
    "Span": {
      "start": 42085,
      "end": 42279
    },
    "index": 220,
    "alignment_index": [
      "220"
    ]
  },
  {
    "Span": {
      "start": 42280,
      "end": 42524
    },
    "index": 221,
    "alignment_index": [
      "221"
    ]
  },
  {
    "Span": {
      "start": 42525,
      "end": 42841
    },
    "index": 222,
    "alignment_index": [
      "222"
    ]
  },
  {
    "Span": {
      "start": 42842,
      "end": 43064
    },
    "index": 223,
    "alignment_index": [
      "223"
    ]
  },
  {
    "Span": {
      "start": 43065,
      "end": 43281
    },
    "index": 224,
    "alignment_index": [
      "224"
    ]
  },
  {
    "Span": {
      "start": 43282,
      "end": 43477
    },
    "index": 225,
    "alignment_index": [
      "225"
    ]
  },
  {
    "Span": {
      "start": 43478,
      "end": 43848
    },
    "index": 226,
    "alignment_index": [
      "226"
    ]
  },
  {
    "Span": {
      "start": 43849,
      "end": 44043
    },
    "index": 227,
    "alignment_index": [
      "227"
    ]
  },
  {
    "Span": {
      "start": 44044,
      "end": 44278
    },
    "index": 228,
    "alignment_index": [
      "228"
    ]
  },
  {
    "Span": {
      "start": 44279,
      "end": 44630
    },
    "index": 229,
    "alignment_index": [
      "229"
    ]
  },
  {
    "Span": {
      "start": 44631,
      "end": 44872
    },
    "index": 230,
    "alignment_index": [
      "230"
    ]
  },
  {
    "Span": {
      "start": 44873,
      "end": 45094
    },
    "index": 231,
    "alignment_index": [
      "231"
    ]
  },
  {
    "Span": {
      "start": 45095,
      "end": 45095
    },
    "index": 232,
    "alignment_index": [
      "232"
    ]
  },
  {
    "Span": {
      "start": 45096,
      "end": 45096
    },
    "index": 233,
    "alignment_index": [
      "233"
    ]
  },
  {
    "Span": {
      "start": 45097,
      "end": 45369
    },
    "index": 234,
    "alignment_index": [
      "234"
    ]
  },
  {
    "Span": {
      "start": 45370,
      "end": 45569
    },
    "index": 235,
    "alignment_index": [
      "235"
    ]
  },
  {
    "Span": {
      "start": 45570,
      "end": 45813
    },
    "index": 236,
    "alignment_index": [
      "236"
    ]
  },
  {
    "Span": {
      "start": 45814,
      "end": 46039
    },
    "index": 237,
    "alignment_index": [
      "237"
    ]
  },
  {
    "Span": {
      "start": 46040,
      "end": 46269
    },
    "index": 238,
    "alignment_index": [
      "238"
    ]
  },
  {
    "Span": {
      "start": 46270,
      "end": 46456
    },
    "index": 239,
    "alignment_index": [
      "239"
    ]
  },
  {
    "Span": {
      "start": 46457,
      "end": 46697
    },
    "index": 240,
    "alignment_index": [
      "240"
    ]
  },
  {
    "Span": {
      "start": 46698,
      "end": 46954
    },
    "index": 241,
    "alignment_index": [
      "241"
    ]
  },
  {
    "Span": {
      "start": 46955,
      "end": 46955
    },
    "index": 242,
    "alignment_index": [
      "242"
    ]
  },
  {
    "Span": {
      "start": 46956,
      "end": 46956
    },
    "index": 243,
    "alignment_index": [
      "243"
    ]
  },
  {
    "Span": {
      "start": 46957,
      "end": 47195
    },
    "index": 244,
    "alignment_index": [
      "244"
    ]
  },
  {
    "Span": {
      "start": 47196,
      "end": 47411
    },
    "index": 245,
    "alignment_index": [
      "245"
    ]
  },
  {
    "Span": {
      "start": 47412,
      "end": 47699
    },
    "index": 246,
    "alignment_index": [
      "246"
    ]
  },
  {
    "Span": {
      "start": 47700,
      "end": 47963
    },
    "index": 247,
    "alignment_index": [
      "247"
    ]
  },
  {
    "Span": {
      "start": 47964,
      "end": 48199
    },
    "index": 248,
    "alignment_index": [
      "248"
    ]
  },
  {
    "Span": {
      "start": 48200,
      "end": 48492
    },
    "index": 249,
    "alignment_index": [
      "249"
    ]
  },
  {
    "Span": {
      "start": 48493,
      "end": 48784
    },
    "index": 250,
    "alignment_index": [
      "250"
    ]
  },
  {
    "Span": {
      "start": 48785,
      "end": 49003
    },
    "index": 251,
    "alignment_index": [
      "251"
    ]
  },
  {
    "Span": {
      "start": 49004,
      "end": 49233
    },
    "index": 252,
    "alignment_index": [
      "252"
    ]
  },
  {
    "Span": {
      "start": 49234,
      "end": 49516
    },
    "index": 253,
    "alignment_index": [
      "253"
    ]
  },
  {
    "Span": {
      "start": 49517,
      "end": 49777
    },
    "index": 254,
    "alignment_index": [
      "254"
    ]
  },
  {
    "Span": {
      "start": 49778,
      "end": 50002
    },
    "index": 255,
    "alignment_index": [
      "255"
    ]
  },
  {
    "Span": {
      "start": 50003,
      "end": 50274
    },
    "index": 256,
    "alignment_index": [
      "256"
    ]
  },
  {
    "Span": {
      "start": 50275,
      "end": 50275
    },
    "index": 257,
    "alignment_index": [
      "257"
    ]
  },
  {
    "Span": {
      "start": 50276,
      "end": 50276
    },
    "index": 258,
    "alignment_index": [
      "258"
    ]
  },
  {
    "Span": {
      "start": 50277,
      "end": 50457
    },
    "index": 259,
    "alignment_index": [
      "259"
    ]
  },
  {
    "Span": {
      "start": 50458,
      "end": 50719
    },
    "index": 260,
    "alignment_index": [
      "260"
    ]
  },
  {
    "Span": {
      "start": 50720,
      "end": 51024
    },
    "index": 261,
    "alignment_index": [
      "261"
    ]
  },
  {
    "Span": {
      "start": 51025,
      "end": 51265
    },
    "index": 262,
    "alignment_index": [
      "262"
    ]
  },
  {
    "Span": {
      "start": 51266,
      "end": 51266
    },
    "index": 263,
    "alignment_index": [
      "263"
    ]
  },
  {
    "Span": {
      "start": 51267,
      "end": 51267
    },
    "index": 264,
    "alignment_index": [
      "264"
    ]
  },
  {
    "Span": {
      "start": 51268,
      "end": 51516
    },
    "index": 265,
    "alignment_index": [
      "265"
    ]
  },
  {
    "Span": {
      "start": 51517,
      "end": 51773
    },
    "index": 266,
    "alignment_index": [
      "266"
    ]
  },
  {
    "Span": {
      "start": 51774,
      "end": 52024
    },
    "index": 267,
    "alignment_index": [
      "267"
    ]
  },
  {
    "Span": {
      "start": 52025,
      "end": 52288
    },
    "index": 268,
    "alignment_index": [
      "268"
    ]
  },
  {
    "Span": {
      "start": 52289,
      "end": 52550
    },
    "index": 269,
    "alignment_index": [
      "269"
    ]
  },
  {
    "Span": {
      "start": 52551,
      "end": 52799
    },
    "index": 270,
    "alignment_index": [
      "270"
    ]
  },
  {
    "Span": {
      "start": 52800,
      "end": 52800
    },
    "index": 271,
    "alignment_index": [
      "271"
    ]
  },
  {
    "Span": {
      "start": 52801,
      "end": 52801
    },
    "index": 272,
    "alignment_index": [
      "272"
    ]
  },
  {
    "Span": {
      "start": 52802,
      "end": 53052
    },
    "index": 273,
    "alignment_index": [
      "273"
    ]
  },
  {
    "Span": {
      "start": 53053,
      "end": 53300
    },
    "index": 274,
    "alignment_index": [
      "274"
    ]
  },
  {
    "Span": {
      "start": 53301,
      "end": 53534
    },
    "index": 275,
    "alignment_index": [
      "275"
    ]
  },
  {
    "Span": {
      "start": 53535,
      "end": 53775
    },
    "index": 276,
    "alignment_index": [
      "276"
    ]
  },
  {
    "Span": {
      "start": 53776,
      "end": 53969
    },
    "index": 277,
    "alignment_index": [
      "277"
    ]
  },
  {
    "Span": {
      "start": 53970,
      "end": 54248
    },
    "index": 278,
    "alignment_index": [
      "278"
    ]
  },
  {
    "Span": {
      "start": 54249,
      "end": 54249
    },
    "index": 279,
    "alignment_index": [
      "279"
    ]
  },
  {
    "Span": {
      "start": 54250,
      "end": 54250
    },
    "index": 280,
    "alignment_index": [
      "280"
    ]
  },
  {
    "Span": {
      "start": 54251,
      "end": 54487
    },
    "index": 281,
    "alignment_index": [
      "281"
    ]
  },
  {
    "Span": {
      "start": 54488,
      "end": 54722
    },
    "index": 282,
    "alignment_index": [
      "282"
    ]
  },
  {
    "Span": {
      "start": 54723,
      "end": 54936
    },
    "index": 283,
    "alignment_index": [
      "283"
    ]
  },
  {
    "Span": {
      "start": 54937,
      "end": 55116
    },
    "index": 284,
    "alignment_index": [
      "284"
    ]
  },
  {
    "Span": {
      "start": 55117,
      "end": 55322
    },
    "index": 285,
    "alignment_index": [
      "285"
    ]
  },
  {
    "Span": {
      "start": 55323,
      "end": 55559
    },
    "index": 286,
    "alignment_index": [
      "286"
    ]
  },
  {
    "Span": {
      "start": 55560,
      "end": 55790
    },
    "index": 287,
    "alignment_index": [
      "287"
    ]
  },
  {
    "Span": {
      "start": 55791,
      "end": 55976
    },
    "index": 288,
    "alignment_index": [
      "288"
    ]
  },
  {
    "Span": {
      "start": 55977,
      "end": 55977
    },
    "index": 289,
    "alignment_index": [
      "289"
    ]
  },
  {
    "Span": {
      "start": 55978,
      "end": 55978
    },
    "index": 290,
    "alignment_index": [
      "290"
    ]
  },
  {
    "Span": {
      "start": 55979,
      "end": 56155
    },
    "index": 291,
    "alignment_index": [
      "291"
    ]
  },
  {
    "Span": {
      "start": 56156,
      "end": 56423
    },
    "index": 292,
    "alignment_index": [
      "292"
    ]
  },
  {
    "Span": {
      "start": 56424,
      "end": 56675
    },
    "index": 293,
    "alignment_index": [
      "293"
    ]
  },
  {
    "Span": {
      "start": 56676,
      "end": 56913
    },
    "index": 294,
    "alignment_index": [
      "294"
    ]
  },
  {
    "Span": {
      "start": 56914,
      "end": 57157
    },
    "index": 295,
    "alignment_index": [
      "295"
    ]
  },
  {
    "Span": {
      "start": 57158,
      "end": 57424
    },
    "index": 296,
    "alignment_index": [
      "296"
    ]
  },
  {
    "Span": {
      "start": 57425,
      "end": 57642
    },
    "index": 297,
    "alignment_index": [
      "297"
    ]
  },
  {
    "Span": {
      "start": 57643,
      "end": 57866
    },
    "index": 298,
    "alignment_index": [
      "298"
    ]
  },
  {
    "Span": {
      "start": 57867,
      "end": 58088
    },
    "index": 299,
    "alignment_index": [
      "299"
    ]
  },
  {
    "Span": {
      "start": 58089,
      "end": 58089
    },
    "index": 300,
    "alignment_index": [
      "300"
    ]
  },
  {
    "Span": {
      "start": 58090,
      "end": 58090
    },
    "index": 301,
    "alignment_index": [
      "301"
    ]
  },
  {
    "Span": {
      "start": 58091,
      "end": 58382
    },
    "index": 302,
    "alignment_index": [
      "302"
    ]
  },
  {
    "Span": {
      "start": 58383,
      "end": 58611
    },
    "index": 303,
    "alignment_index": [
      "303"
    ]
  },
  {
    "Span": {
      "start": 58612,
      "end": 58804
    },
    "index": 304,
    "alignment_index": [
      "304"
    ]
  },
  {
    "Span": {
      "start": 58805,
      "end": 58996
    },
    "index": 305,
    "alignment_index": [
      "305"
    ]
  },
  {
    "Span": {
      "start": 58997,
      "end": 59261
    },
    "index": 306,
    "alignment_index": [
      "306"
    ]
  },
  {
    "Span": {
      "start": 59262,
      "end": 59504
    },
    "index": 307,
    "alignment_index": [
      "307"
    ]
  },
  {
    "Span": {
      "start": 59505,
      "end": 59808
    },
    "index": 308,
    "alignment_index": [
      "308"
    ]
  },
  {
    "Span": {
      "start": 59809,
      "end": 59809
    },
    "index": 309,
    "alignment_index": [
      "309"
    ]
  },
  {
    "Span": {
      "start": 59810,
      "end": 59810
    },
    "index": 310,
    "alignment_index": [
      "310"
    ]
  },
  {
    "Span": {
      "start": 59811,
      "end": 60039
    },
    "index": 311,
    "alignment_index": [
      "311"
    ]
  },
  {
    "Span": {
      "start": 60040,
      "end": 60292
    },
    "index": 312,
    "alignment_index": [
      "312"
    ]
  },
  {
    "Span": {
      "start": 60293,
      "end": 60518
    },
    "index": 313,
    "alignment_index": [
      "313"
    ]
  },
  {
    "Span": {
      "start": 60519,
      "end": 60727
    },
    "index": 314,
    "alignment_index": [
      "314"
    ]
  },
  {
    "Span": {
      "start": 60728,
      "end": 60966
    },
    "index": 315,
    "alignment_index": [
      "315"
    ]
  },
  {
    "Span": {
      "start": 60967,
      "end": 61235
    },
    "index": 316,
    "alignment_index": [
      "316"
    ]
  },
  {
    "Span": {
      "start": 61236,
      "end": 61406
    },
    "index": 317,
    "alignment_index": [
      "317"
    ]
  },
  {
    "Span": {
      "start": 61407,
      "end": 61632
    },
    "index": 318,
    "alignment_index": [
      "318"
    ]
  },
  {
    "Span": {
      "start": 61633,
      "end": 61889
    },
    "index": 319,
    "alignment_index": [
      "319"
    ]
  },
  {
    "Span": {
      "start": 61890,
      "end": 62136
    },
    "index": 320,
    "alignment_index": [
      "320"
    ]
  },
  {
    "Span": {
      "start": 62137,
      "end": 62447
    },
    "index": 321,
    "alignment_index": [
      "321"
    ]
  },
  {
    "Span": {
      "start": 62448,
      "end": 62624
    },
    "index": 322,
    "alignment_index": [
      "322"
    ]
  },
  {
    "Span": {
      "start": 62625,
      "end": 62819
    },
    "index": 323,
    "alignment_index": [
      "323"
    ]
  },
  {
    "Span": {
      "start": 62820,
      "end": 63020
    },
    "index": 324,
    "alignment_index": [
      "324"
    ]
  },
  {
    "Span": {
      "start": 63021,
      "end": 63021
    },
    "index": 325,
    "alignment_index": [
      "325"
    ]
  },
  {
    "Span": {
      "start": 63022,
      "end": 63022
    },
    "index": 326,
    "alignment_index": [
      "326"
    ]
  },
  {
    "Span": {
      "start": 63023,
      "end": 63282
    },
    "index": 327,
    "alignment_index": [
      "327"
    ]
  },
  {
    "Span": {
      "start": 63283,
      "end": 63533
    },
    "index": 328,
    "alignment_index": [
      "328"
    ]
  },
  {
    "Span": {
      "start": 63534,
      "end": 63775
    },
    "index": 329,
    "alignment_index": [
      "329"
    ]
  },
  {
    "Span": {
      "start": 63776,
      "end": 63973
    },
    "index": 330,
    "alignment_index": [
      "330"
    ]
  },
  {
    "Span": {
      "start": 63974,
      "end": 64246
    },
    "index": 331,
    "alignment_index": [
      "331"
    ]
  },
  {
    "Span": {
      "start": 64247,
      "end": 64533
    },
    "index": 332,
    "alignment_index": [
      "332"
    ]
  },
  {
    "Span": {
      "start": 64534,
      "end": 64738
    },
    "index": 333,
    "alignment_index": [
      "333"
    ]
  },
  {
    "Span": {
      "start": 64739,
      "end": 65045
    },
    "index": 334,
    "alignment_index": [
      "334"
    ]
  },
  {
    "Span": {
      "start": 65046,
      "end": 65348
    },
    "index": 335,
    "alignment_index": [
      "335"
    ]
  },
  {
    "Span": {
      "start": 65349,
      "end": 65654
    },
    "index": 336,
    "alignment_index": [
      "336"
    ]
  },
  {
    "Span": {
      "start": 65655,
      "end": 65856
    },
    "index": 337,
    "alignment_index": [
      "337"
    ]
  },
  {
    "Span": {
      "start": 65857,
      "end": 66132
    },
    "index": 338,
    "alignment_index": [
      "338"
    ]
  },
  {
    "Span": {
      "start": 66133,
      "end": 66356
    },
    "index": 339,
    "alignment_index": [
      "339"
    ]
  },
  {
    "Span": {
      "start": 66357,
      "end": 66582
    },
    "index": 340,
    "alignment_index": [
      "340"
    ]
  },
  {
    "Span": {
      "start": 66583,
      "end": 66583
    },
    "index": 341,
    "alignment_index": [
      "341"
    ]
  },
  {
    "Span": {
      "start": 66584,
      "end": 66584
    },
    "index": 342,
    "alignment_index": [
      "342"
    ]
  },
  {
    "Span": {
      "start": 66585,
      "end": 66827
    },
    "index": 343,
    "alignment_index": [
      "343"
    ]
  },
  {
    "Span": {
      "start": 66828,
      "end": 67135
    },
    "index": 344,
    "alignment_index": [
      "344"
    ]
  },
  {
    "Span": {
      "start": 67136,
      "end": 67343
    },
    "index": 345,
    "alignment_index": [
      "345"
    ]
  },
  {
    "Span": {
      "start": 67344,
      "end": 67619
    },
    "index": 346,
    "alignment_index": [
      "346"
    ]
  },
  {
    "Span": {
      "start": 67620,
      "end": 67941
    },
    "index": 347,
    "alignment_index": [
      "347"
    ]
  },
  {
    "Span": {
      "start": 67942,
      "end": 68220
    },
    "index": 348,
    "alignment_index": [
      "348"
    ]
  },
  {
    "Span": {
      "start": 68221,
      "end": 68486
    },
    "index": 349,
    "alignment_index": [
      "349"
    ]
  },
  {
    "Span": {
      "start": 68487,
      "end": 68724
    },
    "index": 350,
    "alignment_index": [
      "350"
    ]
  },
  {
    "Span": {
      "start": 68725,
      "end": 68994
    },
    "index": 351,
    "alignment_index": [
      "351"
    ]
  },
  {
    "Span": {
      "start": 68995,
      "end": 69239
    },
    "index": 352,
    "alignment_index": [
      "352"
    ]
  },
  {
    "Span": {
      "start": 69240,
      "end": 69465
    },
    "index": 353,
    "alignment_index": [
      "353"
    ]
  },
  {
    "Span": {
      "start": 69466,
      "end": 69733
    },
    "index": 354,
    "alignment_index": [
      "354"
    ]
  },
  {
    "Span": {
      "start": 69734,
      "end": 69948
    },
    "index": 355,
    "alignment_index": [
      "355"
    ]
  },
  {
    "Span": {
      "start": 69949,
      "end": 70121
    },
    "index": 356,
    "alignment_index": [
      "356"
    ]
  },
  {
    "Span": {
      "start": 70122,
      "end": 70328
    },
    "index": 357,
    "alignment_index": [
      "357"
    ]
  },
  {
    "Span": {
      "start": 70329,
      "end": 70560
    },
    "index": 358,
    "alignment_index": [
      "358"
    ]
  },
  {
    "Span": {
      "start": 70561,
      "end": 70779
    },
    "index": 359,
    "alignment_index": [
      "359"
    ]
  },
  {
    "Span": {
      "start": 70780,
      "end": 70991
    },
    "index": 360,
    "alignment_index": [
      "360"
    ]
  },
  {
    "Span": {
      "start": 70992,
      "end": 70992
    },
    "index": 361,
    "alignment_index": [
      "361"
    ]
  },
  {
    "Span": {
      "start": 70993,
      "end": 70993
    },
    "index": 362,
    "alignment_index": [
      "362"
    ]
  },
  {
    "Span": {
      "start": 70994,
      "end": 71293
    },
    "index": 363,
    "alignment_index": [
      "363"
    ]
  },
  {
    "Span": {
      "start": 71294,
      "end": 71524
    },
    "index": 364,
    "alignment_index": [
      "364"
    ]
  },
  {
    "Span": {
      "start": 71525,
      "end": 71748
    },
    "index": 365,
    "alignment_index": [
      "365"
    ]
  },
  {
    "Span": {
      "start": 71749,
      "end": 71982
    },
    "index": 366,
    "alignment_index": [
      "366"
    ]
  },
  {
    "Span": {
      "start": 71983,
      "end": 72321
    },
    "index": 367,
    "alignment_index": [
      "367"
    ]
  },
  {
    "Span": {
      "start": 72322,
      "end": 72578
    },
    "index": 368,
    "alignment_index": [
      "368"
    ]
  },
  {
    "Span": {
      "start": 72579,
      "end": 72579
    },
    "index": 369,
    "alignment_index": [
      "369"
    ]
  },
  {
    "Span": {
      "start": 72580,
      "end": 72580
    },
    "index": 370,
    "alignment_index": [
      "370"
    ]
  },
  {
    "Span": {
      "start": 72581,
      "end": 72581
    },
    "index": 371,
    "alignment_index": [
      "371"
    ]
  },
  {
    "Span": {
      "start": 72582,
      "end": 72634
    },
    "index": 372,
    "alignment_index": [
      "372"
    ]
  }
]